wheeler_hale_2015/__init__.py
wheeler_hale_2015/wheeler_hale_2015.py
wheeler_hale_2015-0.1.3.dist-info/DESCRIPTION.rst
wheeler_hale_2015-0.1.3.dist-info/METADATA
wheeler_hale_2015-0.1.3.dist-info/RECORD
wheeler_hale_2015-0.1.3.dist-info/WHEEL
wheeler_hale_2015-0.1.3.dist-info/metadata.json
wheeler_hale_2015-0.1.3.dist-info/top_level.txt
