Metadata-Version: 2.0
Name: wheeler-hale-2015
Version: 0.1.3
Summary: An implementation of Wheeler and Hale's 2015 method for aligning well logs using dynamic warping
Home-page: https://github.com/ar4/wheeler_hale_2015
Author: Alan Richardson
Author-email: UNKNOWN
License: MIT
Platform: UNKNOWN
Classifier: Development Status :: 3 - Alpha
Classifier: Intended Audience :: Science/Research
Classifier: License :: OSI Approved :: MIT License
Classifier: Programming Language :: Python :: 2
Classifier: Programming Language :: Python :: 2.7
Classifier: Programming Language :: Python :: 3
Classifier: Programming Language :: Python :: 3.4
Classifier: Programming Language :: Python :: 3.5
Requires-Dist: fastdtw
Requires-Dist: lasio
Requires-Dist: numpy
Requires-Dist: pandas
Requires-Dist: scipy
